pycrunch/__init__.py
pycrunch/log_configuration.yaml
pycrunch/main.py
pycrunch/multiprocess_child_main.py
pycrunch/web_ui.py
pycrunch/api/__init__.py
pycrunch/api/endpoints.py
pycrunch/api/serializers.py
pycrunch/api/shared.py
pycrunch/api/socket_handlers.py
pycrunch/crossprocess/__init__.py
pycrunch/crossprocess/multiprocess_test_runner.py
pycrunch/crossprocess/tcp_message.py
pycrunch/discovery/__init__.py
pycrunch/discovery/simple.py
pycrunch/introspection/__init__.py
pycrunch/introspection/clock.py
pycrunch/introspection/history.py
pycrunch/introspection/timings.py
pycrunch/pipeline/__init__.py
pycrunch/pipeline/abstract_task.py
pycrunch/pipeline/download_file_task.py
pycrunch/pipeline/execution_pipeline.py
pycrunch/pipeline/file_modification_task.py
pycrunch/pipeline/file_removed_task.py
pycrunch/pipeline/run_test_task.py
pycrunch/plugins/__init__.py
pycrunch/plugins/django_support/__init__.py
pycrunch/plugins/django_support/django_runner_engine.py
pycrunch/plugins/pytest_support/__init__.py
pycrunch/plugins/pytest_support/cleanup_contextmanager.py
pycrunch/plugins/pytest_support/hot_reload.py
pycrunch/plugins/pytest_support/interception_plugin.py
pycrunch/plugins/pytest_support/pytest_runner_engine.py
pycrunch/plugins/simple/__init__.py
pycrunch/plugins/simple/simple_runner_engine.py
pycrunch/runner/__init__.py
pycrunch/runner/_abstract_runner.py
pycrunch/runner/exclusions.py
pycrunch/runner/execution_result.py
pycrunch/runner/interception.py
pycrunch/runner/pipeline_dispatcher.py
pycrunch/runner/test_runner.py
pycrunch/session/__init__.py
pycrunch/session/combined_coverage.py
pycrunch/session/configuration.py
pycrunch/session/diagnostics.py
pycrunch/session/file_map.py
pycrunch/session/state.py
pycrunch/shared/__init__.py
pycrunch/shared/models.py
pycrunch/tests/__init__.py
pycrunch/tests/test_code_generation.py
pycrunch/tests/test_modules_cleanup.py
pycrunch/tests/tests_configuration.py
pycrunch/tests/tests_diagnostics.py
pycrunch/tests/tests_multiprocess.py
pycrunch_engine-0.6.dist-info/LICENCE.txt
pycrunch_engine-0.6.dist-info/METADATA
pycrunch_engine-0.6.dist-info/WHEEL
pycrunch_engine-0.6.dist-info/entry_points.txt
pycrunch_engine-0.6.dist-info/top_level.txt
pycrunch_engine-0.6.dist-info/RECORD
